Flask_Copilot-0.2.0.dist-info/DESCRIPTION.rst
Flask_Copilot-0.2.0.dist-info/METADATA
Flask_Copilot-0.2.0.dist-info/RECORD
Flask_Copilot-0.2.0.dist-info/WHEEL
Flask_Copilot-0.2.0.dist-info/metadata.json
Flask_Copilot-0.2.0.dist-info/top_level.txt
flask_copilot/__init__.py
