Metadata-Version: 2.0
Name: Flask-Copilot
Version: 0.2.0
Summary: Simple navbar generation for Flask applications.
Home-page: https://github.com/jonafato/Flask-Copilot
Author: Jon Banafato
Author-email: jon@jonafato.com
License: BSD
Keywords: flask navigation
Platform: UNKNOWN
Classifier: Development Status :: 4 - Beta
Classifier: Framework :: Flask
Classifier: Intended Audience :: Developers
Classifier: License :: OSI Approved :: BSD License
Classifier: Natural Language :: English
Classifier: Operating System :: OS Independent
Classifier: Programming Language :: Python :: 2
Classifier: Programming Language :: Python :: 2.7
Classifier: Programming Language :: Python :: 3
Classifier: Programming Language :: Python :: 3.3
Classifier: Programming Language :: Python :: 3.4
Classifier: Programming Language :: Python :: 3.5
Requires-Dist: Flask
Requires-Dist: sortedcontainers
